db_creator/__init__.py
db_creator/__main__.py
db_creator/attack.py
db_creator/db_creator.py
db_creator/get_last_layers_activations.py
fingerprints_armor/__init__.py
fingerprints_armor/fingerprints.py
fingerprints_armor/fingerprints_io.py
fingerprints_armor-1.0.1.dist-info/METADATA
fingerprints_armor-1.0.1.dist-info/WHEEL
fingerprints_armor-1.0.1.dist-info/top_level.txt
fingerprints_armor-1.0.1.dist-info/RECORD
