Metadata-Version: 2.1
Name: fingerprints-armor
Version: 1.0.1
Summary: A package implementing the NEURAL FINGERPRINTS FOR ADVERSARIAL ATTACK DETECTION
Home-page: https://github.com/HaimFisher/fingerprints-armor
Author: Haim D. Fisher
Author-email: "Haim D. Fisher" <haimdfisher@gmail.com>
License: MIT
Project-URL: Homepage, https://github.com/HaimFisher/fingerprints-armor
Project-URL: Documentation, https://github.com/HaimFisher/fingerprints-armor/blob/main/README.md
Requires-Python: >=3.10
Requires-Dist: numpy>=2.1.2
Requires-Dist: torch>=2.5.0
Requires-Dist: cleverhans>=4.0.0
Requires-Dist: Pillow>=11.0.0
Requires-Dist: timm>=1.0.11
Requires-Dist: pandas>=2.2.3
Requires-Dist: scikit-learn>=1.5.2
Provides-Extra: dev
Requires-Dist: pytest>=7.0.0; extra == "dev"
Requires-Dist: pytest-cov>=4.0.0; extra == "dev"
Requires-Dist: black>=22.0.0; extra == "dev"
Requires-Dist: isort>=5.0.0; extra == "dev"
Requires-Dist: flake8>=4.0.0; extra == "dev"
